setup.py
mert/__init__.py
mert.egg-info/PKG-INFO
mert.egg-info/SOURCES.txt
mert.egg-info/dependency_links.txt
mert.egg-info/top_level.txt