Metadata-Version: 2.4
Name: mert
Version: 0.1.1
Summary: mert
Author: Mert Sırakaya
Dynamic: author
Dynamic: summary
